README.rst
setup.cfg
setup.py
test/test_cat.py
test/test_cp.py
test/test_find.py
test/test_grep.py
test/test_head.py
test/test_ls.py
test/test_mv.py
test/test_util.py
test/test_watch.py
test/test_wc.py
test/test_which.py
unitils/__init__.py
unitils/cat.py
unitils/cli.py
unitils/cp.py
unitils/find.py
unitils/grep.py
unitils/head.py
unitils/ls.py
unitils/mv.py
unitils/util.py
unitils/watch.py
unitils/wc.py
unitils/which.py
unitils.egg-info/PKG-INFO
unitils.egg-info/SOURCES.txt
unitils.egg-info/dependency_links.txt
unitils.egg-info/entry_points.txt
unitils.egg-info/requires.txt
unitils.egg-info/top_level.txt