Metadata-Version: 1.1
Name: unitils
Version: 0.1.2
Summary: Cross platform utilities I have found to be incredibly useful
Home-page: http://github.com/ilovetux/unitils
Author: iLoveTux
Author-email: me@ilovetux.com
License: GPLv3
Keywords: utility tools cli
Platform: UNKNOWN
Classifier: Development Status :: 4 - Beta
Classifier: Topic :: Utilities
Classifier: License :: OSI Approved :: GNU General Public License v3 (GPLv3)
